ploggy/__init__.py
ploggy/base/__init__.py
ploggy/base/entry.py
ploggy/base/handler.py
ploggy/base/levels.py
ploggy/base/logger.py
ploggy/handlers/__init__.py
ploggy/handlers/json.py
ploggy-0.1.1.dist-info/LICENSE
ploggy-0.1.1.dist-info/METADATA
ploggy-0.1.1.dist-info/WHEEL
ploggy-0.1.1.dist-info/top_level.txt
ploggy-0.1.1.dist-info/RECORD
