Metadata-Version: 2.1
Name: ploggy
Version: 0.1.1
Summary: A dead-simple, extensible logging framework for Python
Home-page: https://github.com/Thunderbottom/ploggy
Author: Chinmay D. Pai
Author-email: chinmaydpai@gmail.com
License: MIT
Keywords: logging,monitoring,framework
Platform: UNKNOWN
Classifier: Intended Audience :: Developers
Classifier: Intended Audience :: System Administrators
Classifier: License :: OSI Approved :: MIT License
Classifier: Programming Language :: Python :: 3.7
Classifier: Programming Language :: Python :: 3.8
Classifier: Programming Language :: Python :: 3.9
Classifier: Topic :: System :: Monitoring
Classifier: Topic :: System :: Logging
Requires-Python: >=3.7.0
